app_store/__init__.py
app_store/app_store_reviews_reader.py
app_store_reviews_reader-1.3.dist-info/LICENSE
app_store_reviews_reader-1.3.dist-info/METADATA
app_store_reviews_reader-1.3.dist-info/WHEEL
app_store_reviews_reader-1.3.dist-info/top_level.txt
app_store_reviews_reader-1.3.dist-info/RECORD
