Metadata-Version: 2.1
Name: app-store-reviews-reader
Version: 1.3
Summary: To fetch app store reviews from publicly available RSS feeds
Home-page: https://github.com/lalitpagaria/app_store_reviews_reader
Author: Lalit Pagaria
Author-email: pagaria.lalit@gmail.com
License: Apache Version 2.0
Platform: UNKNOWN
Classifier: Development Status :: 5 - Production/Stable
Classifier: Intended Audience :: Developers
Classifier: Intended Audience :: Customer Service
Classifier: Intended Audience :: Information Technology
Classifier: License :: OSI Approved :: Apache Software License
Classifier: Operating System :: OS Independent
Classifier: Programming Language :: Python :: 3.9
Classifier: Programming Language :: Python :: 3.10
Classifier: Programming Language :: Python :: 3.11
Classifier: Programming Language :: Python :: 3.12
Classifier: Programming Language :: Python :: 3.13
Classifier: Programming Language :: Python :: 3.14
Classifier: Topic :: Software Development :: Libraries :: Python Modules
Requires-Python: >=3.6.0
License-File: LICENSE
Requires-Dist: feedparser
Requires-Dist: requests
